logic.py
main.py
myservice.py
setup.py
CI_CloudConnector-4.9.dist-info/METADATA
CI_CloudConnector-4.9.dist-info/WHEEL
CI_CloudConnector-4.9.dist-info/top_level.txt
CI_CloudConnector-4.9.dist-info/RECORD
