Metadata-Version: 2.1
Name: CI_CloudConnector
Version: 4.9
Summary: IOT application that collects data from PLC (ModBus or AnB Ethernet/IP) and sends it to the cloud using HTTPS
Home-page: https://trunovate.com/
Author: Yochai
Author-email: 
